{
  "title": "GestureEvents",
  "hierarchy": [],
  "summary": [
    {
      "title": "Enumeration Members",
      "items": [
        14027,
        14028,
        14029
      ]
    }
  ],
  "reflections": {
    "14027": {
      "name": "gestureAttached",
      "type": "EnumMember",
      "url": "/api/enum/GestureEvents#gestureattached",
      "comment": {
        "summary": [
          {
            "kind": "text",
            "text": "When the gesture is attached to the view\nProvides access to the native gesture recognizer for further customization"
          }
        ]
      },
      "flags": {},
      "signatures": [
        {
          "code": "gestureAttached: \"gestureAttached\"",
          "sources": [
            {
              "fileName": "@nativescript/core/ui/gestures/index.d.ts",
              "line": 14,
              "character": 1
            }
          ],
          "comment": {
            "summary": [
              {
                "kind": "text",
                "text": "When the gesture is attached to the view\nProvides access to the native gesture recognizer for further customization"
              }
            ]
          },
          "url": "/api/enum/GestureEvents#gestureattached"
        }
      ]
    },
    "14028": {
      "name": "touchDown",
      "type": "EnumMember",
      "url": "/api/enum/GestureEvents#touchdown",
      "comment": {
        "summary": [
          {
            "kind": "text",
            "text": "When a touch down was detected"
          }
        ]
      },
      "flags": {},
      "signatures": [
        {
          "code": "touchDown: \"touchDown\"",
          "sources": [
            {
              "fileName": "@nativescript/core/ui/gestures/index.d.ts",
              "line": 18,
              "character": 1
            }
          ],
          "comment": {
            "summary": [
              {
                "kind": "text",
                "text": "When a touch down was detected"
              }
            ]
          },
          "url": "/api/enum/GestureEvents#touchdown"
        }
      ]
    },
    "14029": {
      "name": "touchUp",
      "type": "EnumMember",
      "url": "/api/enum/GestureEvents#touchup",
      "comment": {
        "summary": [
          {
            "kind": "text",
            "text": "When a touch up was detected"
          }
        ]
      },
      "flags": {},
      "signatures": [
        {
          "code": "touchUp: \"touchUp\"",
          "sources": [
            {
              "fileName": "@nativescript/core/ui/gestures/index.d.ts",
              "line": 22,
              "character": 1
            }
          ],
          "comment": {
            "summary": [
              {
                "kind": "text",
                "text": "When a touch up was detected"
              }
            ]
          },
          "url": "/api/enum/GestureEvents#touchup"
        }
      ]
    }
  }
}